Workbook

Sheet Assumptions
B2: ChargeFlow Technologies Inc. — Profit Model
B3: Yellow cells are editable assumptions. Replace with real figures as pilot data comes in.
B4: Business model (per site copy): the property owner pays for hardware & installation; ChargeFlow earns an install margin, a share of charging revenue, and a platform fee.
B6: Charging revenue
B7: Charging price ($/kWh) | C7: 0.45 | D7: Illustrative — typical Canadian public L2/DC pricing is ~$0.30-0.60/kWh
B8: Wireless transfer efficiency | C8: 0.7 | D8: From Tier A/B technical spec — energy delivered vs. drawn from grid
B9: Electricity cost ($/kWh, wholesale/commercial) | C9: 0.13 | D9: Ontario commercial rate, illustrative; assumed borne by ChargeFlow (netted from its revenue share)
B11: Drive-thru site (3 charging zones per lane)
B12: Energy delivered per session (kWh) | C12: 0.5 | D12: ~5 min dwell at effective ~6 kW after efficiency losses
B13: Charging sessions per zone per day (Year 1) | C13: 8 | D13: Early-stage EV traffic estimate — grows with EV adoption (see growth rate below)
B14: Zones per drive-thru site | C14: 3
B15: Install cost per drive-thru site (paid by property owner) | C15: 25000 | D15: Midpoint of Tier B estimate ($14,950-$36,570) from technical spec
B17: Parking-stall site (1 charging zone per stall)
B18: Energy delivered per session (kWh) | C18: 4.5 | D18: ~45 min dwell at effective ~6 kW after efficiency losses
B19: Charging sessions per stall per day (Year 1) | C19: 5 | D19: Early-stage estimate for a single marked stall
B20: Install cost per parking site (paid by property owner) | C20: 15000 | D20: Single-zone install - shares less fixed overhead than a 3-zone lane
B22: ChargeFlow's revenue per site
B23: Installation margin ChargeFlow earns | C23: 0.2 | D23: Property owner pays cost + this markup for hardware & install; the markup is ChargeFlow's one-time profit
B24: Platform / monitoring fee per site ($/month) | C24: 150 | D24: Kept 100% by ChargeFlow
B25: Property owner's share of charging revenue | C25: 0.35 | D25: ChargeFlow keeps the remaining 65% of per-session charging revenue
B26: Maintenance & support cost per site ($/year) | C26: 1200 | D26: Borne by ChargeFlow
B27: Operating days per year | C27: 350
B29: Growth & rollout
B30: Annual growth in sessions/site (EV adoption ramp) | C30: 0.2 | D30: Applied economy-wide each year to all sites, mature and new alike
B31: Share of new sites that are drive-thru (vs. parking) | C31: 0.6
B32: First-year revenue ramp factor for newly installed sites | C32: 0.5 | D32: A site installed mid-year earns a partial year of revenue
B33: New sites - Year 1 (pilot) | C33: 1
B34: New sites - Year 2 | C34: 5
B35: New sites - Year 3 | C35: 12
B36: New sites - Year 4 | C36: 22
B37: New sites - Year 5 | C37: 35
B39: Company overhead (team, admin, R&D - not site-specific)
B40: Overhead - Year 1 | C40: 180000 | D40: Founding team, R&D, admin
B41: Overhead - Year 2 | C41: 260000
B42: Overhead - Year 3 | C42: 380000
B43: Overhead - Year 4 | C43: 520000
B44: Overhead - Year 5 | C44: 700000

Sheet Unit Economics
B2: Per-Site Unit Economics (Year-1 baseline, before EV-adoption growth)
B3: What ChargeFlow earns from a single installation. Hardware/install cost is paid by the property owner, not ChargeFlow.
C5: Drive-thru site | D5: Parking site
B6: Sessions per day | C6: =Assumptions!$C$13*Assumptions!$C$14 -> 24 | D6: =Assumptions!$C$19 -> 5
B7: kWh delivered per year | C7: =C6*Assumptions!$C$12*Assumptions!$C$27 -> 4200 | D7: =D6*Assumptions!$C$18*Assumptions!$C$27 -> 7875
B9: Charging revenue billed to driver (kWh x price) | C9: =C7*Assumptions!$C$7 -> 1890 | D9: =D7*Assumptions!$C$7 -> 3543.75
B10: less: property owner's share | C10: =-C9*Assumptions!$C$25 -> -661.5 | D10: =-D9*Assumptions!$C$25 -> -1240.3125
B11: = ChargeFlow's charging revenue | C11: =C9+C10 -> 1228.5 | D11: =D9+D10 -> 2303.4375
B12: Platform / monitoring fee revenue (100% ChargeFlow) | C12: =Assumptions!$C$24*12 -> 1800 | D12: =Assumptions!$C$24*12 -> 1800
B13: ChargeFlow recurring revenue (charging share + platform) | C13: =C11+C12 -> 3028.5 | D13: =D11+D12 -> 4103.4375
B15: Less: electricity cost (grid draw incl. losses) | C15: =-C7/Assumptions!$C$8*Assumptions!$C$9 -> -780 | D15: =-D7/Assumptions!$C$8*Assumptions!$C$9 -> -1462.5
B16: Less: maintenance & support | C16: =-Assumptions!$C$26 -> -1200 | D16: =-Assumptions!$C$26 -> -1200
B17: Recurring site profit (before overhead) | C17: =C13+C15+C16 -> 1048.5 | D17: =D13+D15+D16 -> 1440.9375
B18: Recurring margin (% of ChargeFlow revenue) | C18: =C17/C13 -> 0.346211 | D18: =D17/D13 -> 0.35115376
B20: Install cost (paid by property owner, not ChargeFlow) | C20: =Assumptions!$C$15 -> 25000 | D20: =Assumptions!$C$20 -> 15000
B21: ChargeFlow's one-time installation margin | C21: =C20*Assumptions!$C$23 -> 5000 | D21: =D20*Assumptions!$C$23 -> 3000

Sheet 5-Year Projection
B2: 5-Year Profit Projection
B3: Recurring revenue grows each year with EV adoption. Property owners fund hardware/install; ChargeFlow earns the install margin, not the full cost.
C5: Year 1 | D5: Year 2 | E5: Year 3 | F5: Year 4 | G5: Year 5
B6: New sites added this year | C6: =Assumptions!$C$33 -> 1 | D6: =Assumptions!$C$34 -> 5 | E6: =Assumptions!$C$35 -> 12 | F6: =Assumptions!$C$36 -> 22 | G6: =Assumptions!$C$37 -> 35
B7: of which, new drive-thru sites | C7: =ROUND(C6*Assumptions!$C$31,0) -> 1 | D7: =ROUND(D6*Assumptions!$C$31,0) -> 3 | E7: =ROUND(E6*Assumptions!$C$31,0) -> 7 | F7: =ROUND(F6*Assumptions!$C$31,0) -> 13 | G7: =ROUND(G6*Assumptions!$C$31,0) -> 21
B8: of which, new parking sites | C8: =C6-C7 -> 0 | D8: =D6-D7 -> 2 | E8: =E6-E7 -> 5 | F8: =F6-F7 -> 9 | G8: =G6-G7 -> 14
B10: Cumulative drive-thru sites (end of year) | C10: =0+C7 -> 1 | D10: =C10+D7 -> 4 | E10: =D10+E7 -> 11 | F10: =E10+F7 -> 24 | G10: =F10+G7 -> 45
B11: Cumulative parking sites (end of year) | C11: =0+C8 -> 0 | D11: =C11+D8 -> 2 | E11: =D11+E8 -> 7 | F11: =E11+F8 -> 16 | G11: =F11+G8 -> 30
B12: Total sites (end of year) | C12: =C10+C11 -> 1 | D12: =D10+D11 -> 6 | E12: =E10+E11 -> 18 | F12: =F10+F11 -> 40 | G12: =G10+G11 -> 75
B14: Mature drive-thru sites (installed prior years) | C14: 0 | D14: =C10 -> 1 | E14: =D10 -> 4 | F14: =E10 -> 11 | G14: =F10 -> 24
B15: Mature parking sites (installed prior years) | C15: 0 | D15: =C11 -> 0 | E15: =D11 -> 2 | F15: =E11 -> 7 | G15: =F11 -> 16
B17: Recurring revenue (charging share + platform fees) | C17: =((C14*'Unit Economics'!$C$13+C15*'Unit Economics'!$D$13)+(C7*'Unit Economics'!$C$13+C8*'Unit Economics'!$D$13)*Assumptions!$C$32)*(1+Assumptions!$C$30)^0 -> 1514.25 | D17: =((D14*'Unit Economics'!$C$13+D15*'Unit Economics'!$D$13)+(D7*'Unit Economics'!$C$13+D8*'Unit Economics'!$D$13)*Assumptions!$C$32)*(1+Assumptions!$C$30)^1 -> 14009.625 | E17: =((E14*'Unit Economics'!$C$13+E15*'Unit Economics'!$D$13)+(E7*'Unit Economics'!$C$13+E8*'Unit Economics'!$D$13)*Assumptions!$C$32)*(1+Assumptions!$C$30)^2 -> 59298.075 | F17: =((F14*'Unit Economics'!$C$13+F15*'Unit Economics'!$D$13)+(F7*'Unit Economics'!$C$13+F8*'Unit Economics'!$D$13)*Assumptions!$C$32)*(1+Assumptions!$C$30)^3 -> 173125.35 | G17: =((G14*'Unit Economics'!$C$13+G15*'Unit Economics'!$D$13)+(G7*'Unit Economics'!$C$13+G8*'Unit Economics'!$D$13)*Assumptions!$C$32)*(1+Assumptions!$C$30)^4 -> 412360.89
B18: Recurring site profit (before overhead) | C18: =((C14*'Unit Economics'!$C$17+C15*'Unit Economics'!$D$17)+(C7*'Unit Economics'!$C$17+C8*'Unit Economics'!$D$17)*Assumptions!$C$32)*(1+Assumptions!$C$30)^0 -> 524.25 | D18: =((D14*'Unit Economics'!$C$17+D15*'Unit Economics'!$D$17)+(D7*'Unit Economics'!$C$17+D8*'Unit Economics'!$D$17)*Assumptions!$C$32)*(1+Assumptions!$C$30)^1 -> 4874.625 | E18: =((E14*'Unit Economics'!$C$17+E15*'Unit Economics'!$D$17)+(E7*'Unit Economics'!$C$17+E8*'Unit Economics'!$D$17)*Assumptions!$C$32)*(1+Assumptions!$C$30)^2 -> 20661.075 | F18: =((F14*'Unit Economics'!$C$17+F15*'Unit Economics'!$D$17)+(F7*'Unit Economics'!$C$17+F8*'Unit Economics'!$D$17)*Assumptions!$C$32)*(1+Assumptions!$C$30)^3 -> 60340.95 | G18: =((G14*'Unit Economics'!$C$17+G15*'Unit Economics'!$D$17)+(G7*'Unit Economics'!$C$17+G8*'Unit Economics'!$D$17)*Assumptions!$C$32)*(1+Assumptions!$C$30)^4 -> 143731.2
B19: One-time installation margin (new sites this year) | C19: =C7*'Unit Economics'!$C$21+C8*'Unit Economics'!$D$21 -> 5000 | D19: =D7*'Unit Economics'!$C$21+D8*'Unit Economics'!$D$21 -> 21000 | E19: =E7*'Unit Economics'!$C$21+E8*'Unit Economics'!$D$21 -> 50000 | F19: =F7*'Unit Economics'!$C$21+F8*'Unit Economics'!$D$21 -> 92000 | G19: =G7*'Unit Economics'!$C$21+G8*'Unit Economics'!$D$21 -> 147000
B21: Gross profit (recurring + installation margin) | C21: =C18+C19 -> 5524.25 | D21: =D18+D19 -> 25874.625 | E21: =E18+E19 -> 70661.075 | F21: =F18+F19 -> 152340.95 | G21: =G18+G19 -> 290731.2
B22: Less: company overhead (team, admin, R&D) | C22: =-Assumptions!$C$40 -> -180000 | D22: =-Assumptions!$C$41 -> -260000 | E22: =-Assumptions!$C$42 -> -380000 | F22: =-Assumptions!$C$43 -> -520000 | G22: =-Assumptions!$C$44 -> -700000
B24: Net profit | C24: =C21+C22 -> -174475.75 | D24: =D21+D22 -> -234125.38 | E24: =E21+E22 -> -309338.92 | F24: =F21+F22 -> -367659.05 | G24: =G21+G22 -> -409268.8
B25: Net margin (% of recurring revenue) | C25: =C24/C17 -> -115.22255 | D25: =D24/D17 -> -16.711752 | E25: =E24/E17 -> -5.2166774 | F25: =F24/F17 -> -2.1236581 | G25: =G24/G17 -> -0.9925015
B27: Cumulative net profit | C27: =0+C24 -> -174475.75 | D27: =C27+D24 -> -408601.12 | E27: =D27+E24 -> -717940.05 | F27: =E27+F24 -> -1085599.1 | G27: =F27+G24 -> -1494867.9
